LLMsWebScraper/VERSION
LLMsWebScraper/__init__.py
LLMsWebScraper/scraper.py
LLMsWebScraper/version.py
tests/__init__.py
tests/test_scraper.py
LLMsWebScraper-1.0.3.dist-info/LICENSE
LLMsWebScraper-1.0.3.dist-info/METADATA
LLMsWebScraper-1.0.3.dist-info/WHEEL
LLMsWebScraper-1.0.3.dist-info/top_level.txt
LLMsWebScraper-1.0.3.dist-info/RECORD
