Metadata-Version: 2.1
Name: LLMsWebScraper
Version: 1.0.3
Summary: A Python library to extract structured data from web pages using LLMs.
Home-page: https://github.com/KSDeshappriya/LLMsWebScraper-pip.git
Author: Kavindu Deshappriya
Author-email: ksdeshappriya.official@gmail.com
Classifier: Programming Language :: Python :: 3
Classifier: License :: OSI Approved :: GNU General Public License v3 (GPLv3)
Classifier: Operating System :: OS Independent
Requires-Python: >=3.10
License-File: LICENSE
Requires-Dist: requests>=2.32.3
Requires-Dist: beautifulsoup4>=4.12.3
Requires-Dist: retrying>=1.3.4
Requires-Dist: python-dotenv>=1.0.1
Requires-Dist: langchain>=0.3.13
Requires-Dist: langchain-community>=0.3.13
Requires-Dist: langchain-google-genai>=2.0.7
Requires-Dist: langchain-groq>=0.2.2
Requires-Dist: markdownify>=0.14.1
